Metadata-Version: 2.1
Name: odoo-addon-l10n_fr_das2
Version: 18.0.1.2.0.1
Requires-Python: >=3.10
Requires-Dist: odoo-addon-l10n_fr_cog==18.0.*
Requires-Dist: odoo-addon-l10n_fr_siret_account==18.0.*
Requires-Dist: odoo==18.0.*
Requires-Dist: pyfrdas2>=0.5
Requires-Dist: python-stdnum
Summary: DAS2 (France)
Home-page: https://github.com/OCA/l10n-france
License: AGPL-3
Author: Akretion,Odoo Community Association (OCA)
Author-email: support@odoo-community.org
Classifier: Programming Language :: Python
Classifier: Framework :: Odoo
Classifier: Framework :: Odoo :: 18.0
Classifier: License :: OSI Approved :: GNU Affero General Public License v3
